satanua/__init__.py
satanua/connection_pin.py
satanua/constants.py
satanua/enums.py
satanua/gate.py
satanua/gate_block.py
satanua/id_tracker.py
satanua/switch.py
satanua/test.py
satanua/wire.py
satanua-0.0.3.dist-info/LICENSE
satanua-0.0.3.dist-info/METADATA
satanua-0.0.3.dist-info/WHEEL
satanua-0.0.3.dist-info/top_level.txt
satanua-0.0.3.dist-info/RECORD
