Metadata-Version: 2.1
Name: satanua
Version: 0.0.3
Summary: A library for converting logic formulas to .atanua files
Home-page: https://github.com/YLashko/satanua/
Author: Wym
Author-email: dewreator2@gmail.com
Project-URL: Bug Tracker, https://github.com/YLashko/satanua/issues/
Classifier: Programming Language :: Python :: 3
Classifier: License :: OSI Approved :: MIT License
Classifier: Operating System :: OS Independent
Requires-Python: >=3.10
License-File: LICENSE
